Workbook

Sheet 前端功能清单
A1: 功能编号 | B1: 一级模块 | C1: 二级模块 | D1: 三级模块 | E1: 功能说明 | F1: 设计说明 | G1: 负责人 | H1: 状态 | I1: 备注 | J1: 预估人天 | K1: 实际耗时 | L1: 完成度
A2: F-01 | B2: 管理空间 | C2: 画布管理页 | D2: 画布列表与管理 | E2: 新建画布/导入画布(上传JSON)/画布列表缩略图展示/编辑画布名称/删除画布(二次确认)/下载画布(导出JSON) | H2: 未开始 | J2: =SUMIF(任务清单!A:A,A2,任务清单!I:I) | K2: =SUMIF(任务清单!A:A,A2,任务清单!J:J) | L2: =IF(SUMIF(任务清单!A:A,A2,任务清单!I:I)=0,0,(SUMIFS(任务清单!I:I,任务清单!A:A,A2,任务清单!O:O,"已完成")+SUMIFS(任务清单!I:I,任务清单!A:A,A2,任务清单!O:O,"已取消"))/SUMIF(任务清单!A:A,A2,任务清单!I:I))
A3: F-02 | B3: 管理空间 | C3: 无限画布 | D3: 画布基础操作 | E3: 无限延展创作空间/画布拖拽平移/画布缩放(放大缩小)/适应视图/一键整理/鼠标模式切换(选择/抓手) | H3: 未开始 | J3: =SUMIF(任务清单!A:A,A3,任务清单!I:I) | K3: =SUMIF(任务清单!A:A,A3,任务清单!J:J) | L3: =IF(SUMIF(任务清单!A:A,A3,任务清单!I:I)=0,0,(SUMIFS(任务清单!I:I,任务清单!A:A,A3,任务清单!O:O,"已完成")+SUMIFS(任务清单!I:I,任务清单!A:A,A3,任务清单!O:O,"已取消"))/SUMIF(任务清单!A:A,A3,任务清单!I:I))
A4: F-03 | B4: 管理空间 | C4: 卡片管理 | D4: 卡片(节点)操作 | E4: 新建卡片(左侧按钮/右键/双击3种方式)/卡片拖拽移动/卡片缩放/卡片复制/卡片删除/多卡片框选/卡片编辑(修改内容参数) | H4: 未开始 | J4: =SUMIF(任务清单!A:A,A4,任务清单!I:I) | K4: =SUMIF(任务清单!A:A,A4,任务清单!J:J) | L4: =IF(SUMIF(任务清单!A:A,A4,任务清单!I:I)=0,0,(SUMIFS(任务清单!I:I,任务清单!A:A,A4,任务清单!O:O,"已完成")+SUMIFS(任务清单!I:I,任务清单!A:A,A4,任务清单!O:O,"已取消"))/SUMIF(任务清单!A:A,A4,任务清单!I:I))
A5: F-04 | B5: 管理空间 | C5: 连线系统 | D5: 节点连线功能 | E5: 添加连线(输出端→输入端)/通过输出端呼出模态列表一键创建下游节点/删除连线/连线状态可视化(蓝色有效/灰色无效/黑色选中) | H5: 未开始 | J5: =SUMIF(任务清单!A:A,A5,任务清单!I:I) | K5: =SUMIF(任务清单!A:A,A5,任务清单!J:J) | L5: =IF(SUMIF(任务清单!A:A,A5,任务清单!I:I)=0,0,(SUMIFS(任务清单!I:I,任务清单!A:A,A5,任务清单!O:O,"已完成")+SUMIFS(任务清单!I:I,任务清单!A:A,A5,任务清单!O:O,"已取消"))/SUMIF(任务清单!A:A,A5,任务清单!I:I))
A6: F-05 | B6: 管理空间 | C6: 编组功能 | D6: 节点编组管理 | E6: 框选多卡片编组/编组颜色选择/网格排列(自动网格布局)/水平排列(自动水平布局)/取消编组/下载编组内所有内容 | H6: 未开始 | J6: =SUMIF(任务清单!A:A,A6,任务清单!I:I) | K6: =SUMIF(任务清单!A:A,A6,任务清单!J:J) | L6: =IF(SUMIF(任务清单!A:A,A6,任务清单!I:I)=0,0,(SUMIFS(任务清单!I:I,任务清单!A:A,A6,任务清单!O:O,"已完成")+SUMIFS(任务清单!I:I,任务清单!A:A,A6,任务清单!O:O,"已取消"))/SUMIF(任务清单!A:A,A6,任务清单!I:I))
A7: F-06 | B7: 管理空间 | C7: 堆叠功能 | D7: 节点堆叠管理 | E7: 框选多卡片堆叠为一张卡片(拼图预览)/双击展开堆叠卡片/点击空白重新堆叠/拉出到画布(单独拉出某卡片) | H7: 未开始 | J7: =SUMIF(任务清单!A:A,A7,任务清单!I:I) | K7: =SUMIF(任务清单!A:A,A7,任务清单!J:J) | L7: =IF(SUMIF(任务清单!A:A,A7,任务清单!I:I)=0,0,(SUMIFS(任务清单!I:I,任务清单!A:A,A7,任务清单!O:O,"已完成")+SUMIFS(任务清单!I:I,任务清单!A:A,A7,任务清单!O:O,"已取消"))/SUMIF(任务清单!A:A,A7,任务清单!I:I))
A8: F-07 | B8: 内容卡片 | C8: 文本卡片 | D8: 文本卡片创作 | E8: 文本编辑(Markdown/富文本)/上传参考/AI文本生成/模型选择/生成份数/消耗预览/保存至素材库/生成历史 | H8: 未开始 | J8: =SUMIF(任务清单!A:A,A8,任务清单!I:I) | K8: =SUMIF(任务清单!A:A,A8,任务清单!J:J) | L8: =IF(SUMIF(任务清单!A:A,A8,任务清单!I:I)=0,0,(SUMIFS(任务清单!I:I,任务清单!A:A,A8,任务清单!O:O,"已完成")+SUMIFS(任务清单!I:I,任务清单!A:A,A8,任务清单!O:O,"已取消"))/SUMIF(任务清单!A:A,A8,任务清单!I:I))
A9: F-08 | B9: 内容卡片 | C9: 图片卡片 | D9: 图片卡片创作 | E9: 图片上传/AI图片生成/参数选择(分辨率/风格/份数)/消耗预览/生成历史列表/下载/保存素材库/全屏预览 | H9: 未开始 | J9: =SUMIF(任务清单!A:A,A9,任务清单!I:I) | K9: =SUMIF(任务清单!A:A,A9,任务清单!J:J) | L9: =IF(SUMIF(任务清单!A:A,A9,任务清单!I:I)=0,0,(SUMIFS(任务清单!I:I,任务清单!A:A,A9,任务清单!O:O,"已完成")+SUMIFS(任务清单!I:I,任务清单!A:A,A9,任务清单!O:O,"已取消"))/SUMIF(任务清单!A:A,A9,任务清单!I:I))
A10: F-09 | B10: 内容卡片 | C10: 视频卡片 | D10: 视频卡片创作 | E10: AI生成视频(调用模型)/模型选择/参数选择(运镜/风格/份数)/消耗预览/剪辑(拖动首尾边界)/提取帧(截取当前帧)/超分(选择分辨率)/认证(Seedance 2.0)/下载/存入素材库/全屏展示 | H10: 未开始 | J10: =SUMIF(任务清单!A:A,A10,任务清单!I:I) | K10: =SUMIF(任务清单!A:A,A10,任务清单!J:J) | L10: =IF(SUMIF(任务清单!A:A,A10,任务清单!I:I)=0,0,(SUMIFS(任务清单!I:I,任务清单!A:A,A10,任务清单!O:O,"已完成")+SUMIFS(任务清单!I:I,任务清单!A:A,A10,任务清单!O:O,"已取消"))/SUMIF(任务清单!A:A,A10,任务清单!I:I))
A11: F-10 | B11: 内容卡片 | C11: 音频卡片 | D11: 音频卡片创作 | E11: 上传参考/AI生成音频/模型选择/参数选择(风格/份数)/消耗预览/试听/下载/存入素材库 | H11: 未开始 | J11: =SUMIF(任务清单!A:A,A11,任务清单!I:I) | K11: =SUMIF(任务清单!A:A,A11,任务清单!J:J) | L11: =IF(SUMIF(任务清单!A:A,A11,任务清单!I:I)=0,0,(SUMIFS(任务清单!I:I,任务清单!A:A,A11,任务清单!O:O,"已完成")+SUMIFS(任务清单!I:I,任务清单!A:A,A11,任务清单!O:O,"已取消"))/SUMIF(任务清单!A:A,A11,任务清单!I:I))
A12: F-11 | B12: 生成增强 | C12: 合成节点 | D12: 视频合成节点 | E12: 接收多个视频节点输入/多段视频拼接预览/点击合成完成拼接/消耗预览/下载合成结果 | H12: 未开始 | J12: =SUMIF(任务清单!A:A,A12,任务清单!I:I) | K12: =SUMIF(任务清单!A:A,A12,任务清单!J:J) | L12: =IF(SUMIF(任务清单!A:A,A12,任务清单!I:I)=0,0,(SUMIFS(任务清单!I:I,任务清单!A:A,A12,任务清单!O:O,"已完成")+SUMIFS(任务清单!I:I,任务清单!A:A,A12,任务清单!O:O,"已取消"))/SUMIF(任务清单!A:A,A12,任务清单!I:I))
A13: F-12 | B13: 生成增强 | C13: 导演台 | D13: 导演台节点 | E13: 作为图片/视频节点上游输入/进入导演台编辑页/新增模型(从列表选择)/修改模型参数(场景/人物/颜色/位置/大小/姿势)/拖拽滚轴调整参数/删除模型/调整视角/拍照(生成当前场景截图输出) | H13: 未开始 | J13: =SUMIF(任务清单!A:A,A13,任务清单!I:I) | K13: =SUMIF(任务清单!A:A,A13,任务清单!J:J) | L13: =IF(SUMIF(任务清单!A:A,A13,任务清单!I:I)=0,0,(SUMIFS(任务清单!I:I,任务清单!A:A,A13,任务清单!O:O,"已完成")+SUMIFS(任务清单!I:I,任务清单!A:A,A13,任务清单!O:O,"已取消"))/SUMIF(任务清单!A:A,A13,任务清单!I:I))
... A35: F-34 | B35: 通用 | C35: 状态处理 | D35: 生成状态与异常处理 | E35: 卡片生成状态展示(排队/执行/成功/失败)/失败原因展示/重试/取消/点数不足提示/充值入口/校验必填参数/模型状态 | H35: 未开始 | J35: =SUMIF(任务清单!A:A,A35,任务清单!I:I) | K35: =SUMIF(任务清单!A:A,A35,任务清单!J:J) | L35: =IF(SUMIF(任务清单!A:A,A35,任务清单!I:I)=0,0,(SUMIFS(任务清单!I:I,任务清单!A:A,A35,任务清单!O:O,"已完成")+SUMIFS(任务清单!I:I,任务清单!A:A,A35,任务清单!O:O,"已取消"))/SUMIF(任务清单!A:A,A35,任务清单!I:I))

Sheet 后端功能清单
A1: 功能编号 | B1: 一级模块 | C1: 二级模块 | D1: 三级模块 | E1: 功能说明 | F1: 设计说明 | G1: 负责人 | H1: 状态 | I1: 备注 | J1: 预估人天 | K1: 实际耗时 | L1: 完成度
A2: B-01 | B2: 管理空间 | C2: 画布服务 | D2: 画布CRUD API | E2: 画布创建/查询/更新/删除API/画布列表分页查询/缩略图生成/权限校验(仅所有者操作) | H2: 未开始 | J2: =SUMIF(任务清单!A:A,A2,任务清单!I:I) | K2: =SUMIF(任务清单!A:A,A2,任务清单!J:J) | L2: =IF(SUMIF(任务清单!A:A,A2,任务清单!I:I)=0,0,(SUMIFS(任务清单!I:I,任务清单!A:A,A2,任务清单!O:O,"已完成")+SUMIFS(任务清单!I:I,任务清单!A:A,A2,任务清单!O:O,"已取消"))/SUMIF(任务清单!A:A,A2,任务清单!I:I))
A3: B-02 | B3: 管理空间 | C3: 画布服务 | D3: 画布导入导出API | E3: 画布JSON序列化导出/JSON导入还原/版本号校验/格式兼容性检测/大画布性能优化 | H3: 未开始 | J3: =SUMIF(任务清单!A:A,A3,任务清单!I:I) | K3: =SUMIF(任务清单!A:A,A3,任务清单!J:J) | L3: =IF(SUMIF(任务清单!A:A,A3,任务清单!I:I)=0,0,(SUMIFS(任务清单!I:I,任务清单!A:A,A3,任务清单!O:O,"已完成")+SUMIFS(任务清单!I:I,任务清单!A:A,A3,任务清单!O:O,"已取消"))/SUMIF(任务清单!A:A,A3,任务清单!I:I))
A4: B-03 | B4: 管理空间 | C4: 画布服务 | D4: 画布数据存储API | E4: 节点数据存储(位置/类型/参数/状态)/连线数据存储/编组堆叠数据/画布自动保存/并发写入版本控制 | H4: 未开始 | J4: =SUMIF(任务清单!A:A,A4,任务清单!I:I) | K4: =SUMIF(任务清单!A:A,A4,任务清单!J:J) | L4: =IF(SUMIF(任务清单!A:A,A4,任务清单!I:I)=0,0,(SUMIFS(任务清单!I:I,任务清单!A:A,A4,任务清单!O:O,"已完成")+SUMIFS(任务清单!I:I,任务清单!A:A,A4,任务清单!O:O,"已取消"))/SUMIF(任务清单!A:A,A4,任务清单!I:I))
A5: B-04 | B5: 管理空间 | C5: 连线服务 | D5: 连线与管理API | E5: 连线校验规则(兼容性/自连接/重复连接阻止)/节点类型列表API/下游数据引用解析 | H5: 未开始 | J5: =SUMIF(任务清单!A:A,A5,任务清单!I:I) | K5: =SUMIF(任务清单!A:A,A5,任务清单!J:J) | L5: =IF(SUMIF(任务清单!A:A,A5,任务清单!I:I)=0,0,(SUMIFS(任务清单!I:I,任务清单!A:A,A5,任务清单!O:O,"已完成")+SUMIFS(任务清单!I:I,任务清单!A:A,A5,任务清单!O:O,"已取消"))/SUMIF(任务清单!A:A,A5,任务清单!I:I))
A6: B-05 | B6: 内容生成 | C6: 文本服务 | D6: 文本生成API | E6: AI文本生成接口/提示词校验/Markdown内容存储/上传参考处理 | H6: 未开始 | J6: =SUMIF(任务清单!A:A,A6,任务清单!I:I) | K6: =SUMIF(任务清单!A:A,A6,任务清单!J:J) | L6: =IF(SUMIF(任务清单!A:A,A6,任务清单!I:I)=0,0,(SUMIFS(任务清单!I:I,任务清单!A:A,A6,任务清单!O:O,"已完成")+SUMIFS(任务清单!I:I,任务清单!A:A,A6,任务清单!O:O,"已取消"))/SUMIF(任务清单!A:A,A6,任务清单!I:I))
A7: B-06 | B7: 内容生成 | C7: 图片服务 | D7: 图片生成API | E7: 图片生成接口/多分辨率支持/风格参数映射/多份生成/图片裁剪(单图四宫格九宫格)/超分/扩图/认证(Seedance 2.0)/生成历史存储 | H7: 未开始 | J7: =SUMIF(任务清单!A:A,A7,任务清单!I:I) | K7: =SUMIF(任务清单!A:A,A7,任务清单!J:J) | L7: =IF(SUMIF(任务清单!A:A,A7,任务清单!I:I)=0,0,(SUMIFS(任务清单!I:I,任务清单!A:A,A7,任务清单!O:O,"已完成")+SUMIFS(任务清单!I:I,任务清单!A:A,A7,任务清单!O:O,"已取消"))/SUMIF(任务清单!A:A,A7,任务清单!I:I))
A8: B-07 | B8: 内容生成 | C8: 视频服务 | D8: 视频生成API | E8: 视频生成接口/运镜参数映射/剪辑范围处理/帧提取/超分/认证(Seedance 2.0)/生成历史存储 | H8: 未开始 | J8: =SUMIF(任务清单!A:A,A8,任务清单!I:I) | K8: =SUMIF(任务清单!A:A,A8,任务清单!J:J) | L8: =IF(SUMIF(任务清单!A:A,A8,任务清单!I:I)=0,0,(SUMIFS(任务清单!I:I,任务清单!A:A,A8,任务清单!O:O,"已完成")+SUMIFS(任务清单!I:I,任务清单!A:A,A8,任务清单!O:O,"已取消"))/SUMIF(任务清单!A:A,A8,任务清单!I:I))
A9: B-08 | B9: 内容生成 | C9: 音频服务 | D9: 音频生成API | E9: 音频生成接口/风格参数映射/多份生成/生成历史存储 | H9: 未开始 | J9: =SUMIF(任务清单!A:A,A9,任务清单!I:I) | K9: =SUMIF(任务清单!A:A,A9,任务清单!J:J) | L9: =IF(SUMIF(任务清单!A:A,A9,任务清单!I:I)=0,0,(SUMIFS(任务清单!I:I,任务清单!A:A,A9,任务清单!O:O,"已完成")+SUMIFS(任务清单!I:I,任务清单!A:A,A9,任务清单!O:O,"已取消"))/SUMIF(任务清单!A:A,A9,任务清单!I:I))
A10: B-09 | B10: 生成增强 | C10: 合成服务 | D10: 视频合成API | E10: 多视频节点输入接收/视频拼接/合成任务队列/消耗计算/结果回调 | H10: 未开始 | J10: =SUMIF(任务清单!A:A,A10,任务清单!I:I) | K10: =SUMIF(任务清单!A:A,A10,任务清单!J:J) | L10: =IF(SUMIF(任务清单!A:A,A10,任务清单!I:I)=0,0,(SUMIFS(任务清单!I:I,任务清单!A:A,A10,任务清单!O:O,"已完成")+SUMIFS(任务清单!I:I,任务清单!A:A,A10,任务清单!O:O,"已取消"))/SUMIF(任务清单!A:A,A10,任务清单!I:I))
A11: B-10 | B11: 生成增强 | C11: 导演台服务 | D11: 导演台API | E11: 场景模型管理/人物模型参数存储/位置姿态参数/拖拽参数同步/拍照(截图渲染)/视角调整API | H11: 未开始 | J11: =SUMIF(任务清单!A:A,A11,任务清单!I:I) | K11: =SUMIF(任务清单!A:A,A11,任务清单!J:J) | L11: =IF(SUMIF(任务清单!A:A,A11,任务清单!I:I)=0,0,(SUMIFS(任务清单!I:I,任务清单!A:A,A11,任务清单!O:O,"已完成")+SUMIFS(任务清单!I:I,任务清单!A:A,A11,任务清单!O:O,"已取消"))/SUMIF(任务清单!A:A,A11,任务清单!I:I))
A12: B-11 | B12: 生成服务 | C12: 模型管理 | D12: 模型配置API | E12: 模型列表(文本/图片/视频/音频)/模型信息查询/参数约束/可用状态查询/消耗点数查询 | H12: 未开始 | J12: =SUMIF(任务清单!A:A,A12,任务清单!I:I) | K12: =SUMIF(任务清单!A:A,A12,任务清单!J:J) | L12: =IF(SUMIF(任务清单!A:A,A12,任务清单!I:I)=0,0,(SUMIFS(任务清单!I:I,任务清单!A:A,A12,任务清单!O:O,"已完成")+SUMIFS(任务清单!I:I,任务清单!A:A,A12,任务清单!O:O,"已取消"))/SUMIF(任务清单!A:A,A12,任务清单!I:I))
A13: B-12 | B13: 生成服务 | C13: 任务队列 | D13: 生成任务调度API | E13: 任务创建/参数校验/队列调度/状态管理(排队/执行/成功/失败)/WebSocket状态推送/幂等性控制/重试机制/任务历史存储 | H13: 未开始 | J13: =SUMIF(任务清单!A:A,A13,任务清单!I:I) | K13: =SUMIF(任务清单!A:A,A13,任务清单!J:J) | L13: =IF(SUMIF(任务清单!A:A,A13,任务清单!I:I)=0,0,(SUMIFS(任务清单!I:I,任务清单!A:A,A13,任务清单!O:O,"已完成")+SUMIFS(任务清单!I:I,任务清单!A:A,A13,任务清单!O:O,"已取消"))/SUMIF(任务清单!A:A,A13,任务清单!I:I))
... A48: B-47 | B48: 通用 | C48: 审计日志 | D48: 审计日志API | E48: 敏感操作日志记录(操作人/时间/对象/变更前后值/IP)/日志查询/日志导出 | H48: 未开始 | J48: =SUMIF(任务清单!A:A,A48,任务清单!I:I) | K48: =SUMIF(任务清单!A:A,A48,任务清单!J:J) | L48: =IF(SUMIF(任务清单!A:A,A48,任务清单!I:I)=0,0,(SUMIFS(任务清单!I:I,任务清单!A:A,A48,任务清单!O:O,"已完成")+SUMIFS(任务清单!I:I,任务清单!A:A,A48,任务清单!O:O,"已取消"))/SUMIF(任务清单!A:A,A48,任务清单!I:I))

Sheet 任务清单
A1: 功能编号 | B1: 任务编号 | C1: 阶段 | D1: 任务名称 | E1: 任务目标 | F1: 负责人 | G1: 开始日期 | H1: 结束日期 | I1: 预估(人天) | J1: 实际(人天) | K1: 优先级 | L1: 复杂度 | M1: 前置依赖 | N1: 风险项 | O1: 状态 | P1: 交付物 | Q1: 备注
A2: F-01 | B2: F-01-01 | C2: 画布管理页 | D2: 画布列表页 | E2: 画布列表展示(缩略图/名称/更新时间)/新建画布入口/空状态 | I2: 0.206 | J2: 0 | K2: P0 | L2: 中 | O2: 未开始 | P2: 画布列表页
A3: F-01 | B3: F-01-02 | C3: 画布管理页 | D3: 画布CRUD操作 | E3: 编辑画布名称(行内编辑)/删除画布(二次确认弹窗)/导入画布(上传JSON文件)/下载画布(导出JSON) | I3: 0.206 | J3: 0 | K3: P0 | L3: 中 | M3: F-01-01 | O3: 未开始
A4: F-02 | B4: F-02-01 | C4: 无限画布 | D4: 画布视口组件 | E4: 无限延展创作空间实现/画布拖拽平移/画布缩放(放大缩小)/适应视图/鼠标模式切换(选择/抓手)/快捷键 | I4: 0.343 | J4: 0 | K4: P0 | L4: 高 | M4: F-01-01 | N4: 大画布渲染性能 | O4: 未开始 | P4: 画布视口组件
A5: F-02 | B5: F-02-02 | C5: 无限画布 | D5: 一键整理功能 | E5: 自动排列所有节点/不重叠布局/连线指向保持 | I5: 0.137 | J5: 0 | K5: P0 | L5: 中 | M5: F-02-01 | N5: 布局算法复杂 | O5: 未开始
A6: F-03 | B6: F-03-01 | C6: 卡片管理 | D6: 卡片创建入口 | E6: 新建卡片(左侧添加按钮/右键画布/双击画布空白处3种方式)/卡片类型选择 | I6: 0.206 | J6: 0 | K6: P0 | L6: 中 | M6: F-02-01 | O6: 未开始 | P6: 卡片创建组件
A7: F-03 | B7: F-03-02 | C7: 卡片管理 | D7: 卡片交互操作 | E7: 卡片拖拽移动/卡片缩放/卡片复制/卡片删除/多卡片框选/删除影响提示 | I7: 0.274 | J7: 0 | K7: P0 | L7: 高 | M7: F-03-01 | N7: 节点过多卡顿 | O7: 未开始 | P7: 节点交互系统
A8: F-03 | B8: F-03-03 | C8: 卡片管理 | D8: 卡片编辑功能 | E8: 修改卡片内容/修改卡片参数/编辑面板UI | I8: 0.206 | J8: 0 | K8: P0 | L8: 中 | M8: F-03-02 | O8: 未开始 | P8: 卡片编辑面板
A9: F-04 | B9: F-04-01 | C9: 连线系统 | D9: 连线交互 | E9: 添加连线(输出端拖拽至输入端)/通过输出端呼出模态选择列表/一键创建下游节点并自动连线 | I9: 0.274 | J9: 0 | K9: P0 | L9: 中 | M9: F-03-01 | O9: 未开始 | P9: 连线交互组件
A10: F-04 | B10: F-04-02 | C10: 连线系统 | D10: 连线管理 | E10: 删除连线/连线状态可视化(蓝色有效/灰色无效/黑色选中)/连线曲线渲染 | I10: 0.206 | J10: 0 | K10: P0 | L10: 中 | M10: F-04-01 | O10: 未开始
A11: F-04 | B11: F-04-03 | C11: 连线系统 | D11: 连线校验 | E11: 兼容性校验/阻止自连接/阻止重复连接/不兼容提示 | I11: 0.137 | J11: 0 | K11: P0 | L11: 中 | M11: F-04-01 | O11: 未开始
A12: F-05 | B12: F-05-01 | C12: 编组功能 | D12: 编组创建 | E12: 框选多卡片创建编组/编组颜色选择 | I12: 0.137 | J12: 0 | K12: P1 | L12: 低 | M12: F-03-02 | O12: 未开始 | P12: 编组组件
A13: F-05 | B13: F-05-02 | C13: 编组功能 | D13: 编组布局 | E13: 网格排列(自动网格布局)/水平排列(自动水平布局) | I13: 0.137 | J13: 0 | K13: P1 | L13: 中 | M13: F-05-01 | O13: 未开始
A14: F-05 | B14: F-05-03 | C14: 编组功能 | D14: 编组操作 | E14: 取消编组(保留节点坐标连线)/下载编组内所有内容 | I14: 0.137 | J14: 0 | K14: P1 | L14: 低 | M14: F-05-01 | O14: 未开始
A15: F-06 | B15: F-06-01 | C15: 堆叠功能 | D15: 堆叠创建 | E15: 框选多卡片堆叠为一张卡片(展示拼图预览) | I15: 0.137 | J15: 0 | K15: P1 | L15: 低 | M15: F-03-02 | O15: 未开始 | P15: 堆叠组件
A16: F-06 | B16: F-06-02 | C16: 堆叠功能 | D16: 堆叠交互 | E16: 双击展开堆叠卡片/点击空白重新堆叠/拉出到画布(单独拉出某卡片) | I16: 0.206 | J16: 0 | K16: P1 | L16: 中 | M16: F-06-01 | O16: 未开始
A17: F-07 | B17: F-07-01 | C17: 文本卡片 | D17: 文本卡片组件 | E17: Markdown编辑渲染/提示词输入/上传参考/模型选择/参数设置(生成份数)/消耗预览/提交生成 | I17: 0.274 | J17: 0 | K17: P0 | L17: 中 | M17: F-03-02 | N17: Markdown兼容 | O17: 未开始 | P17: 文本卡片组件
A18: F-07 | B18: F-07-02 | C18: 文本卡片 | D18: 文本生成结果 | E18: 结果展示/编辑/保存素材库/生成历史列表/历史结果切换 | I18: 0.137 | J18: 0 | K18: P0 | L18: 低 | M18: F-07-01 | O18: 未开始
A19: F-08 | B19: F-08-01 | C19: 图片卡片 | D19: 图片卡片组件 | E19: 图片上传/参数选择(分辨率/风格/份数)/模型选择/消耗预览/提交生成 | I19: 0.274 | J19: 0 | K19: P0 | L19: 中 | M19: F-03-02 | O19: 未开始 | P19: 图片卡片组件
A20: F-08 | B20: F-08-02 | C20: 图片卡片 | D20: 图片结果展示 | E20: 生成历史列表/单图四宫格九宫格展示/全屏预览/下载/保存素材库/历史结果切换当前输出 | I20: 0.206 | J20: 0 | K20: P0 | L20: 中 | M20: F-08-01 | O20: 未开始
A21: F-09 | B21: F-09-01 | C21: 视频卡片 | D21: 视频卡片组件 | E21: AI生成视频入口/模型选择/参数选择(运镜/风格/份数)/消耗预览 | I21: 0.206 | J21: 0 | K21: P0 | L21: 中 | M21: F-03-02 | O21: 未开始 | P21: 视频卡片组件
A22: F-09 | B22: F-09-02 | C22: 视频卡片 | D22: 视频编辑操作 | E22: 剪辑(拖动首尾边界确认时间范围)/提取帧(拖动时间轴截取当前帧) | I22: 0.206 | J22: 0 | K22: P1 | L22: 中 | M22: F-09-01 | N22: 视频播放器 | O22: 未开始 | P22: 视频编辑面板
A23: F-09 | B23: F-09-03 | C23: 视频卡片 | D23: 视频结果与认证 | E23: 超分(选择目标分辨率)/认证(Seedance 2.0素材认证)/下载/存入素材库/全屏展示/生成历史 | I23: 0.137 | J23: 0 | K23: P1 | L23: 中 | M23: F-09-02 | N23: Seedance认证接口 | O23: 未开始
A24: F-10 | B24: F-10-01 | C24: 音频卡片 | D24: 音频卡片组件 | E24: 上传参考/AI生成音频/模型选择/参数选择(风格/份数)/消耗预览/试听播放器/下载/存入素材库 | I24: 0.206 | J24: 0 | K24: P0 | L24: 低 | M24: F-03-02 | O24: 未开始 | P24: 音频卡片组件
A25: F-11 | B25: F-11-01 | C25: 合成节点 | D25: 合成节点组件 | E25: 左侧接收多个视频节点输入/多段视频拼接预览列表/调整拼接顺序 | I25: 0.206 | J25: 0 | K25: P1 | L25: 中 | M25: F-09-01 | O25: 未开始 | P25: 合成节点组件
A26: F-11 | B26: F-11-02 | C26: 合成节点 | D26: 合成操作 | E26: 点击合成/消耗预览/合成结果播放与下载 | I26: 0.137 | J26: 0 | K26: P1 | L26: 低 | M26: F-11-01 | O26: 未开始
A27: F-12 | B27: F-12-01 | C27: 导演台 | D27: 导演台编辑页 | E27: 作为图片/视频节点上游输入/进入导演台编辑页面/3D场景渲染 | I27: 0.343 | J27: 0 | K27: P1 | L27: 高 | M27: F-03-02 | N27: 3D渲染性能 | O27: 未开始 | P27: 导演台组件
A28: F-12 | B28: F-12-02 | C28: 导演台 | D28: 模型与参数 | E28: 新增模型(从列表选择)/删除模型/修改基础模型位置与大小/修改人物模型颜色位置姿态/拖拽滚轴调整参数 | I28: 0.206 | J28: 0 | K28: P1 | L28: 中 | M28: F-12-01 | O28: 未开始
A29: F-12 | B29: F-12-03 | C29: 导演台 | D29: 拍照与视角 | E29: 调整视角/拍照(生成当前场景截图作为节点输出) | I29: 0.137 | J29: 0 | K29: P1 | L29: 中 | M29: F-12-02 | O29: 未开始
A30: F-13 | B30: F-13-01 | C30: 素材库 | D30: 素材库侧边栏 | E30: 侧边栏展示/图标模式与列表模式切换 | I30: 0.137 | J30: 0 | K30: P0 | L30: 低 | M30: F-03-01 | O30: 未开始 | P30: 素材库组件
A31: F-13 | B31: F-13-02 | C31: 素材库 | D31: 素材管理操作 | E31: 从画布卡片存入素材库/本地文件上传/拖拽素材到画布/导入画布/下载素材/替换素材(上传新文件)/删除素材(二次确认)/重命名素材/全屏预览素材 | I31: 0.274 | J31: 0 | K31: P0 | L31: 中 | M31: F-13-01 | O31: 未开始
A32: F-13 | B32: F-13-03 | C32: 素材库 | D32: 企业素材转移 | E32: 从个人素材库添加到企业素材库 | I32: 0.069 | J32: 0 | K32: P1 | L32: 低 | M32: F-13-02 | O32: 未开始
A33: F-14 | B33: F-14-01 | C33: Agent对话 | D33: 自然语言交互 | E33: 自然语言输入/Agent理解指令/画布上下文实时展示/全流程自动创作(灵感发散→资料整理→内容生成→结构排版) | I33: 0.343 | J33: 0 | K33: P0 | L33: 高 | M33: F-03-01 | N33: LLM理解准确度 | O33: 未开始 | P33: Agent对话核心
A34: F-14 | B34: F-14-02 | C34: Agent对话 | D34: 对话UI与建议 | E34: 多轮对话界面/创作建议/操作进度展示 | I34: 0.206 | J34: 0 | K34: P0 | L34: 中 | M34: F-14-01 | O34: 未开始
A35: F-15 | B35: F-15-01 | C35: Agent操作 | D35: 对话面板 | E35: 打开Agent对话框(右下角纸鹤图标)/收起对话框/动画过渡 | I35: 0.137 | J35: 0 | K35: P0 | L35: 低 | M35: F-01-01 | O35: 未开始 | P35: Agent面板UI
A36: F-15 | B36: F-15-02 | C36: Agent操作 | D36: 偏好与用量 | E36: 偏好设置(文本/图片/视频模型及分辨率选择)/查看当前对话用量(Token总量/各模型消耗量/点数消耗) | I36: 0.137 | J36: 0 | K36: P0 | L36: 中 | M36: F-15-01 | O36: 未开始
A37: F-16 | B37: F-16-01 | C37: Skill | D37: Skill列表与选择 | E37: Skill选择入口/预设Skill列表浏览/按名称描述搜索Skill/单击选中Skill添加到对话 | I37: 0.137 | J37: 0 | K37: P1 | L37: 低 | M37: F-15-01 | O37: 未开始 | P37: Skill选择UI
A38: F-16 | B38: F-16-02 | C38: Skill | D38: 新建Skill | E38: 空白创建(名称+描述+指令→保存)/从当前对话生成(Agent自动总结→检查修改→保存)/上传Skill文件(选择.md上传/格式校验) | I38: 0.206 | J38: 0 | K38: P1 | L38: 中 | M38: F-16-01 | O38: 未开始 | P38: Skill创建页
A39: F-16 | B39: F-16-03 | C39: Skill | D39: Skill管理 | E39: Skill管理与切换/Skill内容查看/删除Skill | I39: 0.069 | J39: 0 | K39: P1 | L39: 低 | M39: F-16-02 | O39: 未开始
A40: F-17 | B40: F-17-01 | C40: 对话历史 | D40: 对话历史页 | E40: 查看当前画布对话历史/查看其他画布对话历史/新建对话 | I40: 0.137 | J40: 0 | K40: P1 | L40: 低 | M40: F-15-01 | O40: 未开始 | P40: 对话历史页
A41: F-17 | B41: F-17-02 | C41: 对话历史 | D41: 会话片段保存 | E41: 保存会话片段(保存到可复用对话历史)/查看可复用对话历史/复用片段到当前对话 | I41: 0.137 | J41: 0 | K41: P1 | L41: 中 | M41: F-17-01 | O41: 未开始
A42: F-18 | B42: F-18-01 | C42: 记忆系统 | D42: 记忆管理UI | E42: 短期记忆展示(当前session上下文)/长期记忆查看列表/删除长期记忆/记忆偏好标签 | I42: 0.137 | J42: 0 | K42: P2 | L42: 中 | M42: F-17-01 | O42: 未开始 | P42: 记忆管理页
A43: F-19 | B43: F-19-01 | C43: 订阅菜单 | D43: 订阅菜单页 | E43: 查看用户名/ID/个人点数/总可用点数/个人订阅方案展示/订阅个人方案/购买点数/企业方案优势展示/获取顾问联系方式/界面设置(亮暗主题/中英文) | I43: 0.274 | J43: 0 | K43: P0 | L43: 中 | M43: F-01-01 | O43: 未开始 | P43: 订阅菜单页
A44: F-20 | B44: F-20-01 | C44: 分享画布 | D44: 画布分享功能 | E44: 生成共享链接/管理共享状态(开启/关闭)/上传到创意工坊 | I44: 0.137 | J44: 0 | K44: P1 | L44: 低 | M44: F-01-01 | O44: 未开始 | P44: 分享组件
A45: F-21 | B45: F-21-01 | C45: 奖励中心 | D45: 奖励中心页 | E45: 每日签到按钮/签到状态展示/查看每日任务列表和完成状态/领取奖励 | I45: 0.137 | J45: 0 | K45: P1 | L45: 低 | M45: F-01-01 | O45: 未开始 | P45: 奖励中心页
A46: F-22 | B46: F-22-01 | C46: 邀请中心 | D46: 邀请中心页 | E46: 查看我的邀请码和邀请链接/查看邀请人数/邀请成功记录/输入邀请码接受邀请/查看指南/反馈建议 | I46: 0.206 | J46: 0 | K46: P1 | L46: 低 | M46: F-02-01 | O46: 未开始 | P46: 邀请中心页
A47: F-23 | B47: F-23-01 | C47: 历史记录 | D47: 历史记录页 | E47: 历史列表展示(时间/缩略图/模态/模型/点数/提示词)/按提示词搜索/按模型搜索/按模态筛选/按状态筛选/按时间范围筛选/重置/刷新 | I47: 0.274 | J47: 0 | K47: P0 | L47: 中 | M47: F-01-01 | O47: 未开始 | P47: 历史记录页
A48: F-23 | B48: F-23-02 | C48: 历史记录 | D48: 历史记录操作 | E48: 复制提示词/跳转对应画布/查看详情 | I48: 0.069 | J48: 0 | K48: P0 | L48: 低 | M48: F-23-01 | O48: 未开始
A49: F-24 | B49: F-24-01 | C49: 创意广场 | D49: 创意广场页 | E49: 浏览站内公开画布作品/成品预览(上下切换)/查看画布制作过程(节点流程图)/灵感发现/搜索 | I49: 0.274 | J49: 0 | K49: P1 | L49: 中 | M49: F-01-01 | O49: 未开始 | P49: 创意广场页
A50: F-24 | B50: F-24-02 | C50: 创意广场 | D50: 克隆与全屏 | E50: 一键克隆画布到个人工作区/全屏观看/删除自己上传的作品 | I50: 0.137 | J50: 0 | K50: P1 | L50: 低 | M50: F-24-01 | O50: 未开始
A51: F-25 | B51: F-25-01 | C51: 个人中心 | D51: 个人中心页 | E51: 账户身份信息/当前剩余点数/点数消耗情况总览(图表)/每日签到入口/界面设置/退出登录 | I51: 0.206 | J51: 0 | K51: P0 | L51: 低 | M51: F-01-01 | O51: 未开始 | P51: 个人中心页
A52: F-26 | B52: F-26-01 | C52: 企业邀请 | D52: 企业邀请页 | E52: 企业名称/总点数/可分配点数展示/复制企业邀请链接/成员通过链接加入企业 | I52: 0.137 | J52: 0 | K52: P1 | L52: 低 | M52: F-01-01 | O52: 未开始 | P52: 企业邀请页
A53: F-27 | B53: F-27-01 | C53: 成员管理 | D53: 成员管理页 | E53: 团队成员列表/选择特定成员/为成员分配点数(弹窗输入)/回收成员点数(弹窗确认)/将成员移出企业(二次确认) | I53: 0.206 | J53: 0 | K53: P1 | L53: 中 | M53: F-26-01 | O53: 未开始 | P53: 成员管理页
A54: F-28 | B54: F-28-01 | C54: 企业素材库 | D54: 企业素材库页 | E54: 查看企业素材库内容/团队素材共享展示/从个人添加至企业素材库/分配记录统一管理入口 | I54: 0.137 | J54: 0 | K54: P1 | L54: 低 | M54: F-13-02 | O54: 未开始 | P54: 企业素材库页
A55: F-29 | B55: F-29-01 | C55: 分配记录 | D55: 分配记录页 | E55: 查看分配时间/分配类型(分配/回收)/点数数值/操作后账户余额/搜索/导出CSV文件 | I55: 0.137 | J55: 0 | K55: P1 | L55: 低 | M55: F-27-01 | O55: 未开始 | P55: 分配记录页
A56: F-30 | B56: F-30-01 | C56: 点数充值 | D56: 点数充值页 | E56: 企业点数充值页面/套餐选择/支付流程 | I56: 0.137 | J56: 0 | K56: P1 | L56: 低 | M56: F-19-01 | O56: 未开始 | P56: 充值页面
A57: F-31 | B57: F-31-01 | C57: 用量统计 | D57: 用量统计页 | E57: 企业用量/个人用量切换查看/按时间范围筛选/点数消耗可视化图表 | I57: 0.206 | J57: 0 | K57: P1 | L57: 中 | M57: F-29-01 | O57: 未开始 | P57: 用量统计页
A58: F-32 | B58: F-32-01 | C58: 账户设置 | D58: 账户设置页 | E58: 修改企业名称/解散企业(二次确认弹窗+权限校验) | I58: 0.137 | J58: 0 | K58: P1 | L58: 低 | M58: F-26-01 | O58: 未开始 | P58: 账户设置页
A59: F-33 | B59: F-33-01 | C59: 公告查看 | D59: 公告查看 | E59: 查看公告列表/公告详情弹窗/已读未读标记 | I59: 0.069 | J59: 0 | K59: P1 | L59: 低 | M59: F-01-01 | O59: 未开始 | P59: 公告组件
A60: F-34 | B60: F-34-01 | C60: 通用状态 | D60: 生成状态处理 | E60: 生成状态展示(排队/执行/成功/失败)/失败原因展示/重试按钮/取消按钮/点数不足提示/充值入口/必填参数校验提示 | I60: 0.206 | J60: 0 | K60: P0 | L60: 中 | M60: F-07-01 | O60: 未开始
A61: B-01 | B61: B-01-01 | C61: 画布服务 | D61: 画布CRUD API | E61: 画布创建/查询(详情)/更新/删除API/权限校验(仅所有者)/列表(分页/搜索)/缩略图生成 | I61: 0.274 | J61: 0 | K61: P0 | L61: 中 | O61: 未开始 | P61: 画布CRUD API
A62: B-02 | B62: B-02-01 | C62: 画布服务 | D62: 画布导入导出API | E62: JSON序列化导出(节点/连线/参数/坐标)/JSON导入还原/版本号校验/格式兼容性检测/大画布性能优化 | I62: 0.206 | J62: 0 | K62: P0 | L62: 高 | M62: B-01-01 | N62: 大画布序列化 | O62: 未开始 | P62: 导入导出API
A63: B-03 | B63: B-03-01 | C63: 画布服务 | D63: 画布数据存储API | E63: 节点数据增删改(位置/类型/参数/状态)/连线数据增删改/编组堆叠数据存储/自动保存/并发写入版本控制 | I63: 0.274 | J63: 0 | K63: P0 | L63: 高 | M63: B-01-01 | N63: 并发写入冲突 | O63: 未开始 | P63: 画布数据API
A64: B-04 | B64: B-04-01 | C64: 连线服务 | D64: 连线校验API | E64: 兼容性校验规则引擎/自连接检测/重复连接检测/节点类型列表查询/下游数据引用解析/有效状态判断 | I64: 0.165 | J64: 0 | K64: P0 | L64: 中 | M64: B-03-01 | O64: 未开始
A65: B-05 | B65: B-05-01 | C65: 文本服务 | D65: 文本生成API | E65: AI文本生成接口/提示词校验/上传参考文件处理/Markdown内容存储/生成历史存储查询 | I65: 0.165 | J65: 0 | K65: P0 | L65: 中 | M65: B-12-01 | O65: 未开始 | P65: 文本生成API
A66: B-06 | B66: B-06-01 | C66: 图片服务 | D66: 图片生成API | E66: 图片生成接口/多分辨率支持/风格参数映射/多份生成/生成历史存储 | I66: 0.165 | J66: 0 | K66: P0 | L66: 中 | M66: B-12-01 | O66: 未开始 | P66: 图片生成API
A67: B-06 | B67: B-06-02 | C67: 图片服务 | D67: 图片加工API | E67: 图片裁剪(单图/四宫格/九宫格)/超分/扩图/Seedance 2.0认证接口对接 | I67: 0.165 | J67: 0 | K67: P1 | L67: 中 | M67: B-06-01 | N67: 认证接口变化 | O67: 未开始
A68: B-07 | B68: B-07-01 | C68: 视频服务 | D68: 视频生成API | E68: 视频生成接口/运镜参数映射/风格参数/多份生成/生成历史存储 | I68: 0.165 | J68: 0 | K68: P0 | L68: 中 | M68: B-12-01 | O68: 未开始 | P68: 视频生成API
A69: B-07 | B69: B-07-02 | C69: 视频服务 | D69: 视频加工API | E69: 剪辑范围处理/帧提取/超分/Seedance 2.0认证对接 | I69: 0.165 | J69: 0 | K69: P1 | L69: 中 | M69: B-07-01 | O69: 未开始
A70: B-08 | B70: B-08-01 | C70: 音频服务 | D70: 音频生成API | E70: 音频生成接口/风格参数映射/多份生成/生成历史存储/上传参考音频处理 | I70: 0.137 | J70: 0 | K70: P0 | L70: 低 | M70: B-12-01 | O70: 未开始 | P70: 音频生成API
A71: B-09 | B71: B-09-01 | C71: 合成服务 | D71: 合成节点API | E71: 多视频输入接收/拼接顺序管理/合成任务队列/消耗计算/结果回调/合成视频存储 | I71: 0.165 | J71: 0 | K71: P1 | L71: 中 | M71: B-07-01 | N71: 大视频拼接 | O71: 未开始
A72: B-10 | B72: B-10-01 | C72: 导演台 | D72: 导演台API | E72: 场景模型CRUD/人物模型参数存储(颜色/位置/姿势)/拖拽参数实时同步/拍照(3D→2D截图渲染)/视角调整计算 | I72: 0.274 | J72: 0 | K72: P1 | L72: 高 | M72: B-03-01 | N72: 3D渲染性能 | O72: 未开始
A73: B-11 | B73: B-11-01 | C73: 模型管理 | D73: 模型配置API | E73: 模型列表查询(文本/图片/视频/音频分类)/模型详情(名称/类型/参数约束/端点)/模型可用状态/消耗点数查询 | I73: 0.165 | J73: 0 | K73: P0 | L73: 中 | O73: 未开始 | P73: 模型管理API
A74: B-12 | B74: B-12-01 | C74: 任务队列 | D74: 任务调度API | E74: 任务创建(参数校验)/任务入队/队列调度/状态管理(排队→执行→成功/失败)/WebSocket实时状态推送/幂等性控制 | I74: 0.274 | J74: 0 | K74: P0 | L74: 高 | M74: B-11-01 | N74: 队列积压/并发 | O74: 未开始 | P74: 任务调度服务
A75: B-12 | B75: B-12-02 | C75: 任务队列 | D75: 任务重试与取消 | E75: 失败重试机制/手动重试/任务取消/取消后点数退还 | I75: 0.137 | J75: 0 | K75: P0 | L75: 中 | M75: B-12-01 | O75: 未开始
A76: B-13 | B76: B-13-01 | C76: 第三方对接 | D76: 模型适配器 | E76: 文本模型供应商适配/图片模型供应商适配/视频模型供应商适配/音频模型供应商适配/统一适配接口 | I76: 0.274 | J76: 0 | K76: P0 | L76: 高 | M76: B-11-01 | N76: 供应商接口变更 | O76: 未开始 | P76: 模型适配器
A77: B-13 | B77: B-13-02 | C77: 第三方对接 | D77: 容错机制 | E77: 超时重试策略/熔断降级/健康检查/备用模型切换 | I77: 0.137 | J77: 0 | K77: P0 | L77: 高 | M77: B-13-01 | N77: 服务不稳定 | O77: 未开始
A78: B-14 | B78: B-14-01 | C78: 点数管理 | D78: 点数核心API | E78: 个人/企业点数查询/消耗预览计算/预扣/冻结/实际结算/失败退还/异常回滚/事务一致性控制 | I78: 0.274 | J78: 0 | K78: P0 | L78: 高 | M78: B-12-01 | N78: 并发扣费 | O78: 未开始 | P78: 计费核心API
A79: B-15 | B79: B-15-01 | C79: 点数管理 | D79: 点数流水API | E79: 流水记录(动账前自动记录)/按账户查询/按任务追溯/CSV导出/对账/异常告警/分页 | I79: 0.206 | J79: 0 | K79: P0 | L79: 中 | M79: B-14-01 | O79: 未开始 | P79: 流水API
A80: B-16 | B80: B-16-01 | C80: 存储服务 | D80: 文件上传存储API | E80: 文件上传/格式大小校验/恶意内容检测/对象存储集成/CDN加速/文件替换/素材下载 | I80: 0.206 | J80: 0 | K80: P0 | L80: 中 | O80: 未开始 | P80: 存储服务
A81: B-17 | B81: B-17-01 | C81: 素材服务 | D81: 素材管理API | E81: 素材CRUD/分类查询(图片/视频/音频/图标列表模式)/画布节点关联/拖拽引用解析/删除影响检测/个人→企业素材转移API | I81: 0.206 | J81: 0 | K81: P0 | L81: 中 | M81: B-16-01 | O81: 未开始 | P81: 素材管理API
A82: B-18 | B82: B-18-01 | C82: 用户系统 | D82: 注册登录API | E82: 注册/登录/密码加密/Token签发(JWT)/Token刷新/第三方登录/会话管理/退出登录 | I82: 0.274 | J82: 0 | K82: P0 | L82: 中 | N82: 安全合规 | O82: 未开始 | P82: 认证API
A83: B-19 | B83: B-19-01 | C83: 用户系统 | D83: 用户信息API | E83: 用户信息CRUD/偏好设置(亮暗主题/中英文)/个人中心数据聚合/用户名ID查询/订阅方案信息查询/剩余点数查询 | I83: 0.165 | J83: 0 | K83: P0 | L83: 低 | M83: B-18-01 | O83: 未开始 | P83: 用户信息API
A84: B-20 | B84: B-20-01 | C84: 用户系统 | D84: 订阅与充值API | E84: 个人订阅方案管理(查询/购买/续费)/点数购买/订单创建/支付回调处理/企业方案查询/套餐配置查询 | I84: 0.206 | J84: 0 | K84: P0 | L84: 中 | M84: B-18-01 | N84: 支付安全 | O84: 未开始 | P84: 订阅充值API
A85: B-21 | B85: B-21-01 | C85: 用户系统 | D85: 签到与奖励API | E85: 每日签到/连续签到判定/签到奖励发放(点数)/每日任务列表/任务完成判定/奖励领取 | I85: 0.137 | J85: 0 | K85: P1 | L85: 低 | M85: B-18-01 | O85: 未开始
A86: B-22 | B86: B-22-01 | C86: 用户系统 | D86: 邀请系统API | E86: 邀请码生成/邀请链接生成/接受邀请/邀请关系绑定/邀请记录查询/邀请人数统计/邀请奖励发放 | I86: 0.165 | J86: 0 | K86: P1 | L86: 低 | M86: B-18-01 | O86: 未开始
A87: B-23 | B87: B-23-01 | C87: 分享服务 | D87: 画布分享API | E87: 共享链接生成(短链)/共享状态管理(公开/私密/仅链接)/权限控制/上传到创意工坊 | I87: 0.137 | J87: 0 | K87: P1 | L87: 低 | M87: B-01-01 | O87: 未开始
A88: B-24 | B88: B-24-01 | C88: 创意广场 | D88: 创意广场API | E88: 公开画布列表查询(分页/排序/搜索)/画布制作过程节点流程数据/一键克隆(创建独立副本)/删除自己作品/成品预览图 | I88: 0.165 | J88: 0 | K88: P1 | L88: 中 | M88: B-01-01 | O88: 未开始 | P88: 创意广场API
A89: B-25 | B89: B-25-01 | C89: 历史服务 | D89: 任务历史API | E89: 历史记录存储/多维度查询(提示词搜索/模型筛选/模态筛选/状态筛选/时间范围)/分页/统计聚合 | I89: 0.165 | J89: 0 | K89: P0 | L89: 低 | M89: B-12-01 | O89: 未开始 | P89: 历史API
A90: B-26 | B90: B-26-01 | C90: Agent服务 | D90: Agent对话API | E90: SSE流式对话/多轮对话上下文管理/画布上下文构建(节点/连线/选中内容解析)/LLM调用路由/Token统计/模型消耗统计 | I90: 0.274 | J90: 0 | K90: P0 | L90: 高 | M90: B-18-01 | N90: 流式稳定/Token成本 | O90: 未开始 | P90: Agent对话API
A91: B-27 | B91: B-27-01 | C91: Agent服务 | D91: Agent画布操作API | E91: 自然语言指令解析→画布操作映射/节点CRUD/连线管理/编组堆叠/批量操作/重要操作确认机制(点数消耗/删除等)/操作审计日志/全流程自动编排 | I91: 0.274 | J91: 0 | K91: P0 | L91: 高 | M91: B-26-01 | N91: 误操作风险 | O91: 未开始 | P91: Agent操作API
A92: B-28 | B92: B-28-01 | C92: Agent服务 | D92: Skill系统API | E92: Skill CRUD(名称/描述/指令/版本)/预设Skill管理/按名称描述搜索/从对话生成Skill(AI自动总结)/上传.md文件(格式/大小/内容安全校验)/Skill版本管理 | I92: 0.206 | J92: 0 | K92: P1 | L92: 中 | M92: B-26-01 | O92: 未开始 | P92: Skill API
A93: B-29 | B93: B-29-01 | C93: Agent服务 | D93: 会话管理API | E93: 会话CRUD/按画布查询会话列表/跨画布会话查询/保存会话片段/Skill关联/可复用会话管理 | I93: 0.165 | J93: 0 | K93: P1 | L93: 低 | M93: B-26-01 | O93: 未开始
A94: B-30 | B94: B-30-01 | C94: Agent服务 | D94: 记忆系统API | E94: 短期记忆(当前session上下文存储与检索)/长期记忆存储(用户偏好/风格/方向/习惯)/向量嵌入/记忆检索/查看删除长期记忆 | I94: 0.206 | J94: 0 | K94: P2 | L94: 中 | M94: B-26-01 | N94: 向量存储成本 | O94: 未开始
A95: B-31 | B95: B-31-01 | C95: 企业中心 | D95: 企业核心API | E95: 企业创建/企业信息(企业码/名称/总点数/可分配点数)/邀请链接生成/用户通过链接加入/企业角色权限管理(所有者/管理员/成员) | I95: 0.206 | J95: 0 | K95: P1 | L95: 中 | M95: B-18-01 | O95: 未开始 | P95: 企业核心API
A96: B-32 | B96: B-32-01 | C96: 企业中心 | D96: 成员管理API | E96: 成员列表/角色查询/点数分配(分配方减值→接收方增值)/点数回收(回收方减值→企业增值)/移出成员/事务一致性 | I96: 0.206 | J96: 0 | K96: P1 | L96: 中 | M96: B-31-01 | N96: 并发分配 | O96: 未开始 | P96: 成员管理API
A97: B-33 | B97: B-33-01 | C97: 企业中心 | D97: 企业素材库API | E97: 企业素材CRUD/团队共享查询/权限控制(成员读写/管理员全权)/个人→企业素材添加/画布关联 | I97: 0.137 | J97: 0 | K97: P1 | L97: 低 | M97: B-17-01 | O97: 未开始
A98: B-34 | B98: B-34-01 | C98: 企业中心 | D98: 分配记录API | E98: 分配记录查询(时间/类型/点数/余额)/搜索/CSV导出/分页/按时间筛选 | I98: 0.11 | J98: 0 | K98: P1 | L98: 低 | M98: B-32-01 | O98: 未开始
A99: B-35 | B99: B-35-01 | C99: 企业中心 | D99: 企业充值API | E99: 企业点数充值/订单创建/支付回调/充值记录/企业点数余额更新 | I99: 0.137 | J99: 0 | K99: P1 | L99: 低 | M99: B-20-01 | O99: 未开始
A100: B-36 | B100: B-36-01 | C100: 企业中心 | D100: 用量统计API | E100: 企业维度用量聚合/个人维度用量聚合/按时间范围筛选/点数消耗可视化数据(日/周/月)/明细查询 | I100: 0.137 | J100: 0 | K100: P1 | L100: 低 | M100: B-14-01 | O100: 未开始
...
